flair/__init__.py
flair/bed_to_gtf.py
flair/bed_to_sequence.py
flair/call_diffsplice_events.py
flair/collapse_isoforms_precise.py
flair/convert_synthetic_to_genome_bed.py
flair/count_sam_transcripts.py
flair/counts_to_tpm.py
flair/dgd_Hsa_all_v71.tsv
flair/diffExp_deseq2.R
flair/diffExp_drimseq.R
flair/diffSplice_drimSeq.R
flair/diff_iso_usage.py
flair/diffsplice_fishers_exact.py
flair/es_as.py
flair/es_as_inc_excl_to_counts.py
flair/fasta_seq_lengths.py
flair/filter_collapsed_isoforms.py
flair/filter_collapsed_isoforms_from_annotation.py
flair/filter_isoforms_by_proportion_of_gene_expr.py
flair/filter_transcriptome_align.py
flair/flair_align.py
flair/flair_cli.py
flair/flair_collapse.py
flair/flair_combine.py
flair/flair_correct.py
flair/flair_diffExp.py
flair/flair_diffSplice.py
flair/flair_fusion.py
flair/flair_partition.py
flair/flair_quantify.py
flair/flair_transcriptome.py
flair/flair_variants.py
flair/genomic_chimeras.py
flair/get_phase_sets.py
flair/gtf_to_bed.py
flair/identify_annotated_gene.py
flair/identify_gene_isoform.py
flair/junctions_from_sam.py
flair/make_synthetic_fusion_reference.py
flair/mark_intron_retention.py
flair/match_counts.py
flair/normalize_counts_matrix.py
flair/plot_isoform_usage.py
flair/predictProductivity.py
flair/predict_aaseq_withvar.py
flair/pull_starts.py
flair/pycbio/README-pycbio.md
flair/pycbio/__init__.py
flair/pycbio/hgdata/autoSql.py
flair/pycbio/hgdata/bed.py
flair/pycbio/setup.cfg
flair/pycbio/sys/cli.py
flair/pycbio/sys/color.py
flair/pycbio/sys/fileOps.py
flair/pycbio/sys/loggingOps.py
flair/pycbio/sys/objDict.py
flair/pycbio/sys/svgcolors.py
flair/pycbio/tsv/__init__.py
flair/pycbio/tsv/tabFile.py
flair/pycbio/tsv/tsvReader.py
flair/pycbio/tsv/tsvRow.py
flair/remove_internal_priming.py
flair/select_from_bed.py
flair/ssPrep.py
flair/ssUtils.py
flair/subset_unassigned_reads.py
flair/synthetic_splice_sites.py
flair/transcriptomic_chimeras.py
flair_brookslab-3.0.0.dist-info/METADATA
flair_brookslab-3.0.0.dist-info/WHEEL
flair_brookslab-3.0.0.dist-info/entry_points.txt
flair_brookslab-3.0.0.dist-info/licenses/LICENSE.txt
flair_brookslab-3.0.0.dist-info/RECORD
