Metadata-Version: 2.4
Name: flair-brookslab
Version: 3.0.0
Summary: FLAIR is a long-read transcriptomics model building and analysis package
License: BSD 3-clause
License-File: LICENSE.txt
Author: Angela Brooks
Author-email: anbrooks@ucsc.edu
Requires-Python: >=3.12,<3.13
Classifier: License :: Other/Proprietary License
Classifier: Programming Language :: Python :: 3
Classifier: Programming Language :: Python :: 3.12
Provides-Extra: dev
Requires-Dist: bump-my-version (>=1.1.1) ; extra == "dev"
Requires-Dist: flake8 (>=7.1.1) ; extra == "dev"
Requires-Dist: mappy (>=2.28,<3.0)
Requires-Dist: matplotlib (>=3.10.0,<4.0.0)
Requires-Dist: ncls (>=0.0.70,<0.1.0)
Requires-Dist: numpy (>=2.2,<3.0)
Requires-Dist: pipettor (>=1.1.0,<2.0.0)
Requires-Dist: pysam (>=0.23.0,<0.24.0)
Requires-Dist: scipy (>=1.15.1,<2.0.0)
Requires-Dist: setuptools (>=80.2.0,<81.0.0)
Requires-Dist: sphinx (>=8.2.3,<9.0.0) ; extra == "dev"
Requires-Dist: sphinx-rtd-theme (>=3.0.2) ; extra == "dev"
Project-URL: Documentation, https://flair.readthedocs.io/en/latest/
Project-URL: Homepage, https://flair.readthedocs.io/en/latest/
Project-URL: Repository, https://github.com/BrooksLabUCSC/flair/
